odoo/addons/product_type_description/LICENSE
odoo/addons/product_type_description/README.rst
odoo/addons/product_type_description/__init__.py
odoo/addons/product_type_description/__manifest__.py
odoo/addons/product_type_description/images/screen.png
odoo/addons/product_type_description/models/__init__.py
odoo/addons/product_type_description/models/product_template.py
odoo/addons/product_type_description/static/description/icon.png
odoo/addons/product_type_description/static/description/index.html
odoo/addons/product_type_description/tests/TEST_INSTRUCTIONS.rst
odoo/addons/product_type_description/views/product_template.xml
odoo_addon_product_type_description-16.0.1.0.0.dist-info/METADATA
odoo_addon_product_type_description-16.0.1.0.0.dist-info/WHEEL
odoo_addon_product_type_description-16.0.1.0.0.dist-info/top_level.txt
odoo_addon_product_type_description-16.0.1.0.0.dist-info/RECORD
